Workbook

Sheet Shorts ideas
A2: 100 Psychology YouTube Shorts Ideas
A3: Original concept prompts. Research and verify claims before scripting. Durations are suggested seconds. Columns I→AN are filled by the daily Shorts pipeline; Priority sets the order.
I4: PRODUCTION | S4: DAY 7 | AE4: DAY 14 | AI4: DAY 30 | AM4: LEARNING
A5: No. | B5: Theme | C5: Video idea | D5: Opening hook | E5: Content outline | F5: Visual / filming idea | G5: Seconds | H5: Status | I5: Priority | J5: Template fit | K5: Slug | L5: Post date | M5: Weekday | N5: Hook style | O5: Length (s) | P5: Title used | Q5: Source checked | R5: Metricool ID | S5: YT views d7 | T5: YT avg view (s) d7 | U5: YT retention d7 | V5: YT likes d7 | W5: YT comments d7 | X5: YT shares d7 | Y5: IG views d7 | Z5: IG likes d7 | AA5: TT views d7 | AB5: TT likes d7 | AC5: Total views d7 | AD5: Engagement d7 | AE5: YT views d14 | AF5: IG views d14 | AG5: TT views d14 | AH5: Total views d14 | AI5: YT views d30 | AJ5: IG views d30 | AK5: TT views d30 | AL5: Total views d30 | AM5: Verdict d7 | AN5: Lesson / notes
A6: 1 | B6: Cognitive biases | C6: The spotlight effect | D6: Think everyone noticed your awkward moment? | E6: Contrast what you noticed with what others were focused on. | F6: Crowded room with one imagined spotlight | G6: 45 | H6: Published | I6: 1 | J6: Strong | K6: spotlight-effect | L6: 46306 | M6: =IF(L6="","",TEXT(L6,"ddd")) | N6: eyes | O6: 27 | P6: Why It Feels Like Everyone's Watching You | The Spotlight Effect | Q6: Gilovich, Medvec & Savitsky (2000), JPSP 78(2) | R6: 393438157 | U6: =IF(OR(T6="",N(O6)=0),"",T6/O6) | AC6: =IF(COUNT(S6,Y6,AA6)=0,"",SUM(S6,Y6,AA6)) | AD6: =IF(N(AC6)=0,"",SUM(V6,W6,X6,Z6,AB6)/AC6) | AH6: =IF(COUNT(AE6,AF6,AG6)=0,"",SUM(AE6,AF6,AG6)) | AL6: =IF(COUNT(AI6,AJ6,AK6)=0,"",SUM(AI6,AJ6,AK6)) | AM6: =IF(N(AC6)=0,"",IF(COUNT($AC$6:$AC$105)<5,"Too early",IF(AC6>=1.5*MEDIAN($AC$6:$AC$105),"Top",IF(AC6<=0.5*MEDIAN($AC$6:$AC$105),"Low","Average")))) | AN6: Pilot: 16:9 horizontal, YouTube only — not comparable with the vertical Shorts.
A7: 2 | B7: Cognitive biases | C7: Confirmation bias | D7: Could your feed be proving you right on purpose? | E7: Show two people interpreting the same headline differently. | F7: Split-screen headline reactions | G7: 45 | H7: Idea | I7: 11 | J7: Strong | M7: =IF(L7="","",TEXT(L7,"ddd")) | U7: =IF(OR(T7="",N(O7)=0),"",T7/O7) | AC7: =IF(COUNT(S7,Y7,AA7)=0,"",SUM(S7,Y7,AA7)) | AD7: =IF(N(AC7)=0,"",SUM(V7,W7,X7,Z7,AB7)/AC7) | AH7: =IF(COUNT(AE7,AF7,AG7)=0,"",SUM(AE7,AF7,AG7)) | AL7: =IF(COUNT(AI7,AJ7,AK7)=0,"",SUM(AI7,AJ7,AK7)) | AM7: =IF(N(AC7)=0,"",IF(COUNT($AC$6:$AC$105)<5,"Too early",IF(AC7>=1.5*MEDIAN($AC$6:$AC$105),"Top",IF(AC7<=0.5*MEDIAN($AC$6:$AC$105),"Low","Average"))))
A8: 3 | B8: Cognitive biases | C8: The anchoring effect | D8: Why does the first price stick in your head? | E8: Compare a price presented alone with one beside a higher price. | F8: Two price cards | G8: 45 | H8: Idea | I8: 21 | J8: Strong | M8: =IF(L8="","",TEXT(L8,"ddd")) | U8: =IF(OR(T8="",N(O8)=0),"",T8/O8) | AC8: =IF(COUNT(S8,Y8,AA8)=0,"",SUM(S8,Y8,AA8)) | AD8: =IF(N(AC8)=0,"",SUM(V8,W8,X8,Z8,AB8)/AC8) | AH8: =IF(COUNT(AE8,AF8,AG8)=0,"",SUM(AE8,AF8,AG8)) | AL8: =IF(COUNT(AI8,AJ8,AK8)=0,"",SUM(AI8,AJ8,AK8)) | AM8: =IF(N(AC8)=0,"",IF(COUNT($AC$6:$AC$105)<5,"Too early",IF(AC8>=1.5*MEDIAN($AC$6:$AC$105),"Top",IF(AC8<=0.5*MEDIAN($AC$6:$AC$105),"Low","Average"))))
A9: 4 | B9: Cognitive biases | C9: The availability heuristic | D9: Why can a scary headline feel like a common event? | E9: Explain how memorable examples can distort frequency judgments. | F9: News clip illustration and frequency chart | G9: 45 | H9: Idea | I9: 30 | J9: Strong | M9: =IF(L9="","",TEXT(L9,"ddd")) | U9: =IF(OR(T9="",N(O9)=0),"",T9/O9) | AC9: =IF(COUNT(S9,Y9,AA9)=0,"",SUM(S9,Y9,AA9)) | AD9: =IF(N(AC9)=0,"",SUM(V9,W9,X9,Z9,AB9)/AC9) | AH9: =IF(COUNT(AE9,AF9,AG9)=0,"",SUM(AE9,AF9,AG9)) | AL9: =IF(COUNT(AI9,AJ9,AK9)=0,"",SUM(AI9,AJ9,AK9)) | AM9: =IF(N(AC9)=0,"",IF(COUNT($AC$6:$AC$105)<5,"Too early",IF(AC9>=1.5*MEDIAN($AC$6:$AC$105),"Top",IF(AC9<=0.5*MEDIAN($AC$6:$AC$105),"Low","Average"))))
A10: 5 | B10: Cognitive biases | C10: The sunk-cost trap | D10: Would you keep watching a terrible movie just because you paid? | E10: Separate past spending from the next decision. | F10: Movie ticket and exit door | G10: 45 | H10: Idea | I10: 38 | J10: Strong | M10: =IF(L10="","",TEXT(L10,"ddd")) | U10: =IF(OR(T10="",N(O10)=0),"",T10/O10) | AC10: =IF(COUNT(S10,Y10,AA10)=0,"",SUM(S10,Y10,AA10)) | AD10: =IF(N(AC10)=0,"",SUM(V10,W10,X10,Z10,AB10)/AC10) | AH10: =IF(COUNT(AE10,AF10,AG10)=0,"",SUM(AE10,AF10,AG10)) | AL10: =IF(COUNT(AI10,AJ10,AK10)=0,"",SUM(AI10,AJ10,AK10)) | AM10: =IF(N(AC10)=0,"",IF(COUNT($AC$6:$AC$105)<5,"Too early",IF(AC10>=1.5*MEDIAN($AC$6:$AC$105),"Top",IF(AC10<=0.5*MEDIAN($AC$6:$AC$105),"Low","Average"))))
A11: 6 | B11: Cognitive biases | C11: The halo effect | D11: Can one good trait change your whole impression? | E11: Show how polished appearance can influence unrelated judgments. | F11: Same résumé with different presentation | G11: 45 | H11: Idea | I11: 45 | J11: Strong | M11: =IF(L11="","",TEXT(L11,"ddd")) | U11: =IF(OR(T11="",N(O11)=0),"",T11/O11) | AC11: =IF(COUNT(S11,Y11,AA11)=0,"",SUM(S11,Y11,AA11)) | AD11: =IF(N(AC11)=0,"",SUM(V11,W11,X11,Z11,AB11)/AC11) | AH11: =IF(COUNT(AE11,AF11,AG11)=0,"",SUM(AE11,AF11,AG11)) | AL11: =IF(COUNT(AI11,AJ11,AK11)=0,"",SUM(AI11,AJ11,AK11)) | AM11: =IF(N(AC11)=0,"",IF(COUNT($AC$6:$AC$105)<5,"Too early",IF(AC11>=1.5*MEDIAN($AC$6:$AC$105),"Top",IF(AC11<=0.5*MEDIAN($AC$6:$AC$105),"Low","Average"))))
A12: 7 | B12: Cognitive biases | C12: Hindsight bias | D12: Why does everything seem obvious afterward? | E12: Reveal a prediction before and after an outcome. | F12: Sealed prediction envelope | G12: 45 | H12: Idea | I12: 52 | J12: Strong | M12: =IF(L12="","",TEXT(L12,"ddd")) | U12: =IF(OR(T12="",N(O12)=0),"",T12/O12) | AC12: =IF(COUNT(S12,Y12,AA12)=0,"",SUM(S12,Y12,AA12)) | AD12: =IF(N(AC12)=0,"",SUM(V12,W12,X12,Z12,AB12)/AC12) | AH12: =IF(COUNT(AE12,AF12,AG12)=0,"",SUM(AE12,AF12,AG12)) | AL12: =IF(COUNT(AI12,AJ12,AK12)=0,"",SUM(AI12,AJ12,AK12)) | AM12: =IF(N(AC12)=0,"",IF(COUNT($AC$6:$AC$105)<5,"Too early",IF(AC12>=1.5*MEDIAN($AC$6:$AC$105),"Top",IF(AC12<=0.5*MEDIAN($AC$6:$AC$105),"Low","Average"))))
A13: 8 | B13: Cognitive biases | C13: Framing effects | D13: Would you choose differently if the wording changed? | E13: Present equivalent outcomes as gains and losses. | F13: Matching percentage cards | G13: 45 | H13: Idea | I13: 58 | J13: Strong | M13: =IF(L13="","",TEXT(L13,"ddd")) | U13: =IF(OR(T13="",N(O13)=0),"",T13/O13) | AC13: =IF(COUNT(S13,Y13,AA13)=0,"",SUM(S13,Y13,AA13)) | AD13: =IF(N(AC13)=0,"",SUM(V13,W13,X13,Z13,AB13)/AC13) | AH13: =IF(COUNT(AE13,AF13,AG13)=0,"",SUM(AE13,AF13,AG13)) | AL13: =IF(COUNT(AI13,AJ13,AK13)=0,"",SUM(AI13,AJ13,AK13)) | AM13: =IF(N(AC13)=0,"",IF(COUNT($AC$6:$AC$105)<5,"Too early",IF(AC13>=1.5*MEDIAN($AC$6:$AC$105),"Top",IF(AC13<=0.5*MEDIAN($AC$6:$AC$105),"Low","Average"))))
A14: 9 | B14: Cognitive biases | C14: The default effect | D14: Did you choose it, or was it already selected? | E14: Compare an opt-in form with a preselected option. | F14: Mock settings screen | G14: 45 | H14: Idea | I14: 64 | J14: Strong | M14: =IF(L14="","",TEXT(L14,"ddd")) | U14: =IF(OR(T14="",N(O14)=0),"",T14/O14) | AC14: =IF(COUNT(S14,Y14,AA14)=0,"",SUM(S14,Y14,AA14)) | AD14: =IF(N(AC14)=0,"",SUM(V14,W14,X14,Z14,AB14)/AC14) | AH14: =IF(COUNT(AE14,AF14,AG14)=0,"",SUM(AE14,AF14,AG14)) | AL14: =IF(COUNT(AI14,AJ14,AK14)=0,"",SUM(AI14,AJ14,AK14)) | AM14: =IF(N(AC14)=0,"",IF(COUNT($AC$6:$AC$105)<5,"Too early",IF(AC14>=1.5*MEDIAN($AC$6:$AC$105),"Top",IF(AC14<=0.5*MEDIAN($AC$6:$AC$105),"Low","Average"))))
A15: 10 | B15: Cognitive biases | C15: The fundamental attribution error | D15: Why is their mistake a personality flaw, but yours has a reason? | E15: Compare explanations for your lateness and someone else's. | F15: Two late arrivals | G15: 45 | H15: Idea | I15: 69 | J15: Strong | M15: =IF(L15="","",TEXT(L15,"ddd")) | U15: =IF(OR(T15="",N(O15)=0),"",T15/O15) | AC15: =IF(COUNT(S15,Y15,AA15)=0,"",SUM(S15,Y15,AA15)) | AD15: =IF(N(AC15)=0,"",SUM(V15,W15,X15,Z15,AB15)/AC15) | AH15: =IF(COUNT(AE15,AF15,AG15)=0,"",SUM(AE15,AF15,AG15)) | AL15: =IF(COUNT(AI15,AJ15,AK15)=0,"",SUM(AI15,AJ15,AK15)) | AM15: =IF(N(AC15)=0,"",IF(COUNT($AC$6:$AC$105)<5,"Too early",IF(AC15>=1.5*MEDIAN($AC$6:$AC$105),"Top",IF(AC15<=0.5*MEDIAN($AC$6:$AC$105),"Low","Average"))))
A16: 11 | B16: Memory and learning | C16: Recognition versus recall | D16: Recognizing the answer isn't the same as knowing it. | E16: Compare multiple choice with explaining from a blank page. | F16: Quiz cards | G16: 45 | H16: Scheduled | I16: 2 | J16: Strong | K16: recognition-vs-recall | L16: 46307 | M16: =IF(L16="","",TEXT(L16,"ddd")) | N16: thoughts | O16: 35 | P16: Why You Recognize Answers You Can't Remember #shorts | Q16: Bahrick, Bahrick & Wittlinger 1975, J Exp Psych: General 104(1):54-75 (ERIC EJ113581); 90% recognition over ~15 yrs and steady free-recall decline per Conway, Cohen & Stanhope 1991 review + Simply Psychology. Recall % left out (secondary sources disagree). | R16: 3390233992092010605 | U16: =IF(OR(T16="",N(O16)=0),"",T16/O16) | AC16: =IF(COUNT(S16,Y16,AA16)=0,"",SUM(S16,Y16,AA16)) | AD16: =IF(N(AC16)=0,"",SUM(V16,W16,X16,Z16,AB16)/AC16) | AH16: =IF(COUNT(AE16,AF16,AG16)=0,"",SUM(AE16,AF16,AG16)) | AL16: =IF(COUNT(AI16,AJ16,AK16)=0,"",SUM(AI16,AJ16,AK16)) | AM16: =IF(N(AC16)=0,"",IF(COUNT($AC$6:$AC$105)<5,"Too early",IF(AC16>=1.5*MEDIAN($AC$6:$AC$105),"Top",IF(AC16<=0.5*MEDIAN($AC$6:$AC$105),"Low","Average"))))
A17: 12 | B17: Memory and learning | C17: The testing effect | D17: Can a mini quiz help more than another reread? | E17: Show a study session with retrieval and later checking. | F17: Notebook closed then reopened | G17: 45 | H17: Idea | I17: 12 | J17: Strong | M17: =IF(L17="","",TEXT(L17,"ddd")) | U17: =IF(OR(T17="",N(O17)=0),"",T17/O17) | AC17: =IF(COUNT(S17,Y17,AA17)=0,"",SUM(S17,Y17,AA17)) | AD17: =IF(N(AC17)=0,"",SUM(V17,W17,X17,Z17,AB17)/AC17) | AH17: =IF(COUNT(AE17,AF17,AG17)=0,"",SUM(AE17,AF17,AG17)) | AL17: =IF(COUNT(AI17,AJ17,AK17)=0,"",SUM(AI17,AJ17,AK17)) | AM17: =IF(N(AC17)=0,"",IF(COUNT($AC$6:$AC$105)<5,"Too early",IF(AC17>=1.5*MEDIAN($AC$6:$AC$105),"Top",IF(AC17<=0.5*MEDIAN($AC$6:$AC$105),"Low","Average"))))
A18: 13 | B18: Memory and learning | C18: Spacing your practice | D18: What happens when studying is spread across the week? | E18: Compare spaced sessions with one long cram session. | F18: Two study calendars | G18: 45 | H18: Idea | I18: 22 | J18: Strong | M18: =IF(L18="","",TEXT(L18,"ddd")) | U18: =IF(OR(T18="",N(O18)=0),"",T18/O18) | AC18: =IF(COUNT(S18,Y18,AA18)=0,"",SUM(S18,Y18,AA18)) | AD18: =IF(N(AC18)=0,"",SUM(V18,W18,X18,Z18,AB18)/AC18) | AH18: =IF(COUNT(AE18,AF18,AG18)=0,"",SUM(AE18,AF18,AG18)) | AL18: =IF(COUNT(AI18,AJ18,AK18)=0,"",SUM(AI18,AJ18,AK18)) | AM18: =IF(N(AC18)=0,"",IF(COUNT($AC$6:$AC$105)<5,"Too early",IF(AC18>=1.5*MEDIAN($AC$6:$AC$105),"Top",IF(AC18<=0.5*MEDIAN($AC$6:$AC$105),"Low","Average"))))
A19: 14 | B19: Memory and learning | C19: Interleaving practice | D19: Why mix problem types while studying? | E19: Show choosing a method rather than repeating one method. | F19: Shuffled problem cards | G19: 45 | H19: Idea | I19: 31 | J19: Strong | M19: =IF(L19="","",TEXT(L19,"ddd")) | U19: =IF(OR(T19="",N(O19)=0),"",T19/O19) | AC19: =IF(COUNT(S19,Y19,AA19)=0,"",SUM(S19,Y19,AA19)) | AD19: =IF(N(AC19)=0,"",SUM(V19,W19,X19,Z19,AB19)/AC19) | AH19: =IF(COUNT(AE19,AF19,AG19)=0,"",SUM(AE19,AF19,AG19)) | AL19: =IF(COUNT(AI19,AJ19,AK19)=0,"",SUM(AI19,AJ19,AK19)) | AM19: =IF(N(AC19)=0,"",IF(COUNT($AC$6:$AC$105)<5,"Too early",IF(AC19>=1.5*MEDIAN($AC$6:$AC$105),"Top",IF(AC19<=0.5*MEDIAN($AC$6:$AC$105),"Low","Average"))))
A20: 15 | B20: Memory and learning | C20: Memory is reconstructive | D20: Can two honest people remember the same event differently? | E20: Show how recall can rebuild details rather than replay video. | F20: Two drawings of one scene | G20: 45 | H20: Idea | I20: 39 | J20: Strong | M20: =IF(L20="","",TEXT(L20,"ddd")) | U20: =IF(OR(T20="",N(O20)=0),"",T20/O20) | AC20: =IF(COUNT(S20,Y20,AA20)=0,"",SUM(S20,Y20,AA20)) | AD20: =IF(N(AC20)=0,"",SUM(V20,W20,X20,Z20,AB20)/AC20) | AH20: =IF(COUNT(AE20,AF20,AG20)=0,"",SUM(AE20,AF20,AG20)) | AL20: =IF(COUNT(AI20,AJ20,AK20)=0,"",SUM(AI20,AJ20,AK20)) | AM20: =IF(N(AC20)=0,"",IF(COUNT($AC$6:$AC$105)<5,"Too early",IF(AC20>=1.5*MEDIAN($AC$6:$AC$105),"Top",IF(AC20<=0.5*MEDIAN($AC$6:$AC$105),"Low","Average"))))
A21: 16 | B21: Memory and learning | C21: The misinformation effect | D21: Can a question change what someone remembers? | E21: Compare neutral wording with a question suggesting a detail. | F21: Two interview captions | G21: 45 | H21: Idea | I21: 46 | J21: Strong | M21: =IF(L21="","",TEXT(L21,"ddd")) | U21: =IF(OR(T21="",N(O21)=0),"",T21/O21) | AC21: =IF(COUNT(S21,Y21,AA21)=0,"",SUM(S21,Y21,AA21)) | AD21: =IF(N(AC21)=0,"",SUM(V21,W21,X21,Z21,AB21)/AC21) | AH21: =IF(COUNT(AE21,AF21,AG21)=0,"",SUM(AE21,AF21,AG21)) | AL21: =IF(COUNT(AI21,AJ21,AK21)=0,"",SUM(AI21,AJ21,AK21)) | AM21: =IF(N(AC21)=0,"",IF(COUNT($AC$6:$AC$105)<5,"Too early",IF(AC21>=1.5*MEDIAN($AC$6:$AC$105),"Top",IF(AC21<=0.5*MEDIAN($AC$6:$AC$105),"Low","Average"))))
A22: 17 | B22: Memory and learning | C22: Tip-of-the-tongue moments | D22: You know the word, so why won't it come out? | E22: Explore partial access to a word and its related clues. | F22: Missing-word bubble | G22: 45 | H22: Idea | I22: 53 | J22: Strong | M22: =IF(L22="","",TEXT(L22,"ddd")) | U22: =IF(OR(T22="",N(O22)=0),"",T22/O22) | AC22: =IF(COUNT(S22,Y22,AA22)=0,"",SUM(S22,Y22,AA22)) | AD22: =IF(N(AC22)=0,"",SUM(V22,W22,X22,Z22,AB22)/AC22) | AH22: =IF(COUNT(AE22,AF22,AG22)=0,"",SUM(AE22,AF22,AG22)) | AL22: =IF(COUNT(AI22,AJ22,AK22)=0,"",SUM(AI22,AJ22,AK22)) | AM22: =IF(N(AC22)=0,"",IF(COUNT($AC$6:$AC$105)<5,"Too early",IF(AC22>=1.5*MEDIAN($AC$6:$AC$105),"Top",IF(AC22<=0.5*MEDIAN($AC$6:$AC$105),"Low","Average"))))
A23: 18 | B23: Memory and learning | C23: The serial-position effect | D23: Which items from this list will you remember? | E23: Run a short list demo and discuss beginning and end advantages. | F23: Ten words flashed onscreen | G23: 45 | H23: Idea | I23: 59 | J23: Strong | M23: =IF(L23="","",TEXT(L23,"ddd")) | U23: =IF(OR(T23="",N(O23)=0),"",T23/O23) | AC23: =IF(COUNT(S23,Y23,AA23)=0,"",SUM(S23,Y23,AA23)) | AD23: =IF(N(AC23)=0,"",SUM(V23,W23,X23,Z23,AB23)/AC23) | AH23: =IF(COUNT(AE23,AF23,AG23)=0,"",SUM(AE23,AF23,AG23)) | AL23: =IF(COUNT(AI23,AJ23,AK23)=0,"",SUM(AI23,AJ23,AK23)) | AM23: =IF(N(AC23)=0,"",IF(COUNT($AC$6:$AC$105)<5,"Too early",IF(AC23>=1.5*MEDIAN($AC$6:$AC$105),"Top",IF(AC23<=0.5*MEDIAN($AC$6:$AC$105),"Low","Average"))))
A24: 19 | B24: Memory and learning | C24: Context and recall | D24: Why can returning to a room remind you of something? | E24: Explore how environmental cues can support recall. | F24: Doorway and reminder prop | G24: 45 | H24: Idea | I24: 65 | J24: Strong | M24: =IF(L24="","",TEXT(L24,"ddd")) | U24: =IF(OR(T24="",N(O24)=0),"",T24/O24) | AC24: =IF(COUNT(S24,Y24,AA24)=0,"",SUM(S24,Y24,AA24)) | AD24: =IF(N(AC24)=0,"",SUM(V24,W24,X24,Z24,AB24)/AC24) | AH24: =IF(COUNT(AE24,AF24,AG24)=0,"",SUM(AE24,AF24,AG24)) | AL24: =IF(COUNT(AI24,AJ24,AK24)=0,"",SUM(AI24,AJ24,AK24)) | AM24: =IF(N(AC24)=0,"",IF(COUNT($AC$6:$AC$105)<5,"Too early",IF(AC24>=1.5*MEDIAN($AC$6:$AC$105),"Top",IF(AC24<=0.5*MEDIAN($AC$6:$AC$105),"Low","Average"))))
A25: 20 | B25: Memory and learning | C25: The illusion of understanding | D25: Can you explain how a zipper actually works? | E25: Ask for an explanation before showing the mechanism. | F25: Zipper close-up | G25: 45 | H25: Idea | I25: 70 | J25: Strong | M25: =IF(L25="","",TEXT(L25,"ddd")) | U25: =IF(OR(T25="",N(O25)=0),"",T25/O25) | AC25: =IF(COUNT(S25,Y25,AA25)=0,"",SUM(S25,Y25,AA25)) | AD25: =IF(N(AC25)=0,"",SUM(V25,W25,X25,Z25,AB25)/AC25) | AH25: =IF(COUNT(AE25,AF25,AG25)=0,"",SUM(AE25,AF25,AG25)) | AL25: =IF(COUNT(AI25,AJ25,AK25)=0,"",SUM(AI25,AJ25,AK25)) | AM25: =IF(N(AC25)=0,"",IF(COUNT($AC$6:$AC$105)<5,"Too early",IF(AC25>=1.5*MEDIAN($AC$6:$AC$105),"Top",IF(AC25<=0.5*MEDIAN($AC$6:$AC$105),"Low","Average"))))
A26: 21 | B26: Attention and perception | C26: The Stroop challenge | D26: Say the ink color, not the word. | E26: Run a brief demo of competing automatic responses. | F26: Colored color words | G26: 45 | H26: Idea | I26: 72 | J26: Weak | M26: =IF(L26="","",TEXT(L26,"ddd")) | U26: =IF(OR(T26="",N(O26)=0),"",T26/O26) | AC26: =IF(COUNT(S26,Y26,AA26)=0,"",SUM(S26,Y26,AA26)) | AD26: =IF(N(AC26)=0,"",SUM(V26,W26,X26,Z26,AB26)/AC26) | AH26: =IF(COUNT(AE26,AF26,AG26)=0,"",SUM(AE26,AF26,AG26)) | AL26: =IF(COUNT(AI26,AJ26,AK26)=0,"",SUM(AI26,AJ26,AK26)) | AM26: =IF(N(AC26)=0,"",IF(COUNT($AC$6:$AC$105)<5,"Too early",IF(AC26>=1.5*MEDIAN($AC$6:$AC$105),"Top",IF(AC26<=0.5*MEDIAN($AC$6:$AC$105),"Low","Average"))))
A27: 22 | B27: Attention and perception | C27: Inattentional blindness | D27: Can you miss something obvious while concentrating? | E27: Give a counting task with an unexpected background change. | F27: Original ball-counting animation | G27: 45 | H27: Idea | I27: 3 | J27: Strong | M27: =IF(L27="","",TEXT(L27,"ddd")) | U27: =IF(OR(T27="",N(O27)=0),"",T27/O27) | AC27: =IF(COUNT(S27,Y27,AA27)=0,"",SUM(S27,Y27,AA27)) | AD27: =IF(N(AC27)=0,"",SUM(V27,W27,X27,Z27,AB27)/AC27) | AH27: =IF(COUNT(AE27,AF27,AG27)=0,"",SUM(AE27,AF27,AG27)) | AL27: =IF(COUNT(AI27,AJ27,AK27)=0,"",SUM(AI27,AJ27,AK27)) | AM27: =IF(N(AC27)=0,"",IF(COUNT($AC$6:$AC$105)<5,"Too early",IF(AC27>=1.5*MEDIAN($AC$6:$AC$105),"Top",IF(AC27<=0.5*MEDIAN($AC$6:$AC$105),"Low","Average"))))
A28: 23 | B28: Attention and perception | C28: Change blindness | D28: What changed between these two scenes? | E28: Reveal a changed object and explain limits of attention. | F28: Alternating room illustrations | G28: 45 | H28: Idea | I28: 79 | J28: Weak | M28: =IF(L28="","",TEXT(L28,"ddd")) | U28: =IF(OR(T28="",N(O28)=0),"",T28/O28) | AC28: =IF(COUNT(S28,Y28,AA28)=0,"",SUM(S28,Y28,AA28)) | AD28: =IF(N(AC28)=0,"",SUM(V28,W28,X28,Z28,AB28)/AC28) | AH28: =IF(COUNT(AE28,AF28,AG28)=0,"",SUM(AE28,AF28,AG28)) | AL28: =IF(COUNT(AI28,AJ28,AK28)=0,"",SUM(AI28,AJ28,AK28)) | AM28: =IF(N(AC28)=0,"",IF(COUNT($AC$6:$AC$105)<5,"Too early",IF(AC28>=1.5*MEDIAN($AC$6:$AC$105),"Top",IF(AC28<=0.5*MEDIAN($AC$6:$AC$105),"Low","Average"))))
... A105: 100 | B105: Psychology myths and interactive demos | C105: Psychology claim checklist | D105: Before sharing a psychology fact, ask these three questions. | E105: Ask about evidence, population, and limits of the conclusion. | F105: Three-question checklist | G105: 45 | H105: Idea | I105: 78 | J105: Weak | M105: =IF(L105="","",TEXT(L105,"ddd")) | U105: =IF(OR(T105="",N(O105)=0),"",T105/O105) | AC105: =IF(COUNT(S105,Y105,AA105)=0,"",SUM(S105,Y105,AA105)) | AD105: =IF(N(AC105)=0,"",SUM(V105,W105,X105,Z105,AB105)/AC105) | AH105: =IF(COUNT(AE105,AF105,AG105)=0,"",SUM(AE105,AF105,AG105)) | AL105: =IF(COUNT(AI105,AJ105,AK105)=0,"",SUM(AI105,AJ105,AK105)) | AM105: =IF(N(AC105)=0,"",IF(COUNT($AC$6:$AC$105)<5,"Too early",IF(AC105>=1.5*MEDIAN($AC$6:$AC$105),"Top",IF(AC105<=0.5*MEDIAN($AC$6:$AC$105),"Low","Average"))))

Sheet Summary
A1: What's working
A2: Averages over published Shorts with day-7 numbers. Updates as the pipeline fills the tracker.
A4: Theme | B4: Published | C4: Avg views d7 | D4: Avg retention d7 | E4: Avg engagement d7 | F4: Avg views d30
A5: Cognitive biases | B5: =COUNTIFS('Shorts ideas'!$B$6:$B$105,$A5,'Shorts ideas'!$H$6:$H$105,"Published") | C5: =IFERROR(AVERAGEIFS('Shorts ideas'!$AC$6:$AC$105,'Shorts ideas'!$B$6:$B$105,$A5,'Shorts ideas'!$AC$6:$AC$105,">0"),"") | D5: =IFERROR(AVERAGEIFS('Shorts ideas'!$U$6:$U$105,'Shorts ideas'!$B$6:$B$105,$A5,'Shorts ideas'!$U$6:$U$105,">0"),"") | E5: =IFERROR(AVERAGEIFS('Shorts ideas'!$AD$6:$AD$105,'Shorts ideas'!$B$6:$B$105,$A5,'Shorts ideas'!$AD$6:$AD$105,">0"),"") | F5: =IFERROR(AVERAGEIFS('Shorts ideas'!$AL$6:$AL$105,'Shorts ideas'!$B$6:$B$105,$A5,'Shorts ideas'!$AL$6:$AL$105,">0"),"")
A6: Memory and learning | B6: =COUNTIFS('Shorts ideas'!$B$6:$B$105,$A6,'Shorts ideas'!$H$6:$H$105,"Published") | C6: =IFERROR(AVERAGEIFS('Shorts ideas'!$AC$6:$AC$105,'Shorts ideas'!$B$6:$B$105,$A6,'Shorts ideas'!$AC$6:$AC$105,">0"),"") | D6: =IFERROR(AVERAGEIFS('Shorts ideas'!$U$6:$U$105,'Shorts ideas'!$B$6:$B$105,$A6,'Shorts ideas'!$U$6:$U$105,">0"),"") | E6: =IFERROR(AVERAGEIFS('Shorts ideas'!$AD$6:$AD$105,'Shorts ideas'!$B$6:$B$105,$A6,'Shorts ideas'!$AD$6:$AD$105,">0"),"") | F6: =IFERROR(AVERAGEIFS('Shorts ideas'!$AL$6:$AL$105,'Shorts ideas'!$B$6:$B$105,$A6,'Shorts ideas'!$AL$6:$AL$105,">0"),"")
A7: Attention and perception | B7: =COUNTIFS('Shorts ideas'!$B$6:$B$105,$A7,'Shorts ideas'!$H$6:$H$105,"Published") | C7: =IFERROR(AVERAGEIFS('Shorts ideas'!$AC$6:$AC$105,'Shorts ideas'!$B$6:$B$105,$A7,'Shorts ideas'!$AC$6:$AC$105,">0"),"") | D7: =IFERROR(AVERAGEIFS('Shorts ideas'!$U$6:$U$105,'Shorts ideas'!$B$6:$B$105,$A7,'Shorts ideas'!$U$6:$U$105,">0"),"") | E7: =IFERROR(AVERAGEIFS('Shorts ideas'!$AD$6:$AD$105,'Shorts ideas'!$B$6:$B$105,$A7,'Shorts ideas'!$AD$6:$AD$105,">0"),"") | F7: =IFERROR(AVERAGEIFS('Shorts ideas'!$AL$6:$AL$105,'Shorts ideas'!$B$6:$B$105,$A7,'Shorts ideas'!$AL$6:$AL$105,">0"),"")
A8: Habits and motivation | B8: =COUNTIFS('Shorts ideas'!$B$6:$B$105,$A8,'Shorts ideas'!$H$6:$H$105,"Published") | C8: =IFERROR(AVERAGEIFS('Shorts ideas'!$AC$6:$AC$105,'Shorts ideas'!$B$6:$B$105,$A8,'Shorts ideas'!$AC$6:$AC$105,">0"),"") | D8: =IFERROR(AVERAGEIFS('Shorts ideas'!$U$6:$U$105,'Shorts ideas'!$B$6:$B$105,$A8,'Shorts ideas'!$U$6:$U$105,">0"),"") | E8: =IFERROR(AVERAGEIFS('Shorts ideas'!$AD$6:$AD$105,'Shorts ideas'!$B$6:$B$105,$A8,'Shorts ideas'!$AD$6:$AD$105,">0"),"") | F8: =IFERROR(AVERAGEIFS('Shorts ideas'!$AL$6:$AL$105,'Shorts ideas'!$B$6:$B$105,$A8,'Shorts ideas'!$AL$6:$AL$105,">0"),"")
A9: Emotions and self-awareness | B9: =COUNTIFS('Shorts ideas'!$B$6:$B$105,$A9,'Shorts ideas'!$H$6:$H$105,"Published") | C9: =IFERROR(AVERAGEIFS('Shorts ideas'!$AC$6:$AC$105,'Shorts ideas'!$B$6:$B$105,$A9,'Shorts ideas'!$AC$6:$AC$105,">0"),"") | D9: =IFERROR(AVERAGEIFS('Shorts ideas'!$U$6:$U$105,'Shorts ideas'!$B$6:$B$105,$A9,'Shorts ideas'!$U$6:$U$105,">0"),"") | E9: =IFERROR(AVERAGEIFS('Shorts ideas'!$AD$6:$AD$105,'Shorts ideas'!$B$6:$B$105,$A9,'Shorts ideas'!$AD$6:$AD$105,">0"),"") | F9: =IFERROR(AVERAGEIFS('Shorts ideas'!$AL$6:$AL$105,'Shorts ideas'!$B$6:$B$105,$A9,'Shorts ideas'!$AL$6:$AL$105,">0"),"")
A10: Relationships and communication | B10: =COUNTIFS('Shorts ideas'!$B$6:$B$105,$A10,'Shorts ideas'!$H$6:$H$105,"Published") | C10: =IFERROR(AVERAGEIFS('Shorts ideas'!$AC$6:$AC$105,'Shorts ideas'!$B$6:$B$105,$A10,'Shorts ideas'!$AC$6:$AC$105,">0"),"") | D10: =IFERROR(AVERAGEIFS('Shorts ideas'!$U$6:$U$105,'Shorts ideas'!$B$6:$B$105,$A10,'Shorts ideas'!$U$6:$U$105,">0"),"") | E10: =IFERROR(AVERAGEIFS('Shorts ideas'!$AD$6:$AD$105,'Shorts ideas'!$B$6:$B$105,$A10,'Shorts ideas'!$AD$6:$AD$105,">0"),"") | F10: =IFERROR(AVERAGEIFS('Shorts ideas'!$AL$6:$AL$105,'Shorts ideas'!$B$6:$B$105,$A10,'Shorts ideas'!$AL$6:$AL$105,">0"),"")
A11: Social psychology | B11: =COUNTIFS('Shorts ideas'!$B$6:$B$105,$A11,'Shorts ideas'!$H$6:$H$105,"Published") | C11: =IFERROR(AVERAGEIFS('Shorts ideas'!$AC$6:$AC$105,'Shorts ideas'!$B$6:$B$105,$A11,'Shorts ideas'!$AC$6:$AC$105,">0"),"") | D11: =IFERROR(AVERAGEIFS('Shorts ideas'!$U$6:$U$105,'Shorts ideas'!$B$6:$B$105,$A11,'Shorts ideas'!$U$6:$U$105,">0"),"") | E11: =IFERROR(AVERAGEIFS('Shorts ideas'!$AD$6:$AD$105,'Shorts ideas'!$B$6:$B$105,$A11,'Shorts ideas'!$AD$6:$AD$105,">0"),"") | F11: =IFERROR(AVERAGEIFS('Shorts ideas'!$AL$6:$AL$105,'Shorts ideas'!$B$6:$B$105,$A11,'Shorts ideas'!$AL$6:$AL$105,">0"),"")
A12: Self-image and confidence | B12: =COUNTIFS('Shorts ideas'!$B$6:$B$105,$A12,'Shorts ideas'!$H$6:$H$105,"Published") | C12: =IFERROR(AVERAGEIFS('Shorts ideas'!$AC$6:$AC$105,'Shorts ideas'!$B$6:$B$105,$A12,'Shorts ideas'!$AC$6:$AC$105,">0"),"") | D12: =IFERROR(AVERAGEIFS('Shorts ideas'!$U$6:$U$105,'Shorts ideas'!$B$6:$B$105,$A12,'Shorts ideas'!$U$6:$U$105,">0"),"") | E12: =IFERROR(AVERAGEIFS('Shorts ideas'!$AD$6:$AD$105,'Shorts ideas'!$B$6:$B$105,$A12,'Shorts ideas'!$AD$6:$AD$105,">0"),"") | F12: =IFERROR(AVERAGEIFS('Shorts ideas'!$AL$6:$AL$105,'Shorts ideas'!$B$6:$B$105,$A12,'Shorts ideas'!$AL$6:$AL$105,">0"),"")
A13: Digital life and consumer behavior | B13: =COUNTIFS('Shorts ideas'!$B$6:$B$105,$A13,'Shorts ideas'!$H$6:$H$105,"Published") | C13: =IFERROR(AVERAGEIFS('Shorts ideas'!$AC$6:$AC$105,'Shorts ideas'!$B$6:$B$105,$A13,'Shorts ideas'!$AC$6:$AC$105,">0"),"") | D13: =IFERROR(AVERAGEIFS('Shorts ideas'!$U$6:$U$105,'Shorts ideas'!$B$6:$B$105,$A13,'Shorts ideas'!$U$6:$U$105,">0"),"") | E13: =IFERROR(AVERAGEIFS('Shorts ideas'!$AD$6:$AD$105,'Shorts ideas'!$B$6:$B$105,$A13,'Shorts ideas'!$AD$6:$AD$105,">0"),"") | F13: =IFERROR(AVERAGEIFS('Shorts ideas'!$AL$6:$AL$105,'Shorts ideas'!$B$6:$B$105,$A13,'Shorts ideas'!$AL$6:$AL$105,">0"),"")
A14: Psychology myths and interactive demos | B14: =COUNTIFS('Shorts ideas'!$B$6:$B$105,$A14,'Shorts ideas'!$H$6:$H$105,"Published") | C14: =IFERROR(AVERAGEIFS('Shorts ideas'!$AC$6:$AC$105,'Shorts ideas'!$B$6:$B$105,$A14,'Shorts ideas'!$AC$6:$AC$105,">0"),"") | D14: =IFERROR(AVERAGEIFS('Shorts ideas'!$U$6:$U$105,'Shorts ideas'!$B$6:$B$105,$A14,'Shorts ideas'!$U$6:$U$105,">0"),"") | E14: =IFERROR(AVERAGEIFS('Shorts ideas'!$AD$6:$AD$105,'Shorts ideas'!$B$6:$B$105,$A14,'Shorts ideas'!$AD$6:$AD$105,">0"),"") | F14: =IFERROR(AVERAGEIFS('Shorts ideas'!$AL$6:$AL$105,'Shorts ideas'!$B$6:$B$105,$A14,'Shorts ideas'!$AL$6:$AL$105,">0"),"")
A16: Hook style | B16: Published | C16: Avg views d7 | D16: Avg retention d7 | E16: Avg engagement d7 | F16: Avg views d30
A17: eyes | B17: =COUNTIFS('Shorts ideas'!$N$6:$N$105,$A17,'Shorts ideas'!$H$6:$H$105,"Published") | C17: =IFERROR(AVERAGEIFS('Shorts ideas'!$AC$6:$AC$105,'Shorts ideas'!$N$6:$N$105,$A17,'Shorts ideas'!$AC$6:$AC$105,">0"),"") | D17: =IFERROR(AVERAGEIFS('Shorts ideas'!$U$6:$U$105,'Shorts ideas'!$N$6:$N$105,$A17,'Shorts ideas'!$U$6:$U$105,">0"),"") | E17: =IFERROR(AVERAGEIFS('Shorts ideas'!$AD$6:$AD$105,'Shorts ideas'!$N$6:$N$105,$A17,'Shorts ideas'!$AD$6:$AD$105,">0"),"") | F17: =IFERROR(AVERAGEIFS('Shorts ideas'!$AL$6:$AL$105,'Shorts ideas'!$N$6:$N$105,$A17,'Shorts ideas'!$AL$6:$AL$105,">0"),"")
A18: thoughts | B18: =COUNTIFS('Shorts ideas'!$N$6:$N$105,$A18,'Shorts ideas'!$H$6:$H$105,"Published") | C18: =IFERROR(AVERAGEIFS('Shorts ideas'!$AC$6:$AC$105,'Shorts ideas'!$N$6:$N$105,$A18,'Shorts ideas'!$AC$6:$AC$105,">0"),"") | D18: =IFERROR(AVERAGEIFS('Shorts ideas'!$U$6:$U$105,'Shorts ideas'!$N$6:$N$105,$A18,'Shorts ideas'!$U$6:$U$105,">0"),"") | E18: =IFERROR(AVERAGEIFS('Shorts ideas'!$AD$6:$AD$105,'Shorts ideas'!$N$6:$N$105,$A18,'Shorts ideas'!$AD$6:$AD$105,">0"),"") | F18: =IFERROR(AVERAGEIFS('Shorts ideas'!$AL$6:$AL$105,'Shorts ideas'!$N$6:$N$105,$A18,'Shorts ideas'!$AL$6:$AL$105,">0"),"")
A20: Weekday | B20: Published | C20: Avg views d7 | D20: Avg retention d7 | E20: Avg engagement d7 | F20: Avg views d30
A21: Mon | B21: =COUNTIFS('Shorts ideas'!$M$6:$M$105,$A21,'Shorts ideas'!$H$6:$H$105,"Published") | C21: =IFERROR(AVERAGEIFS('Shorts ideas'!$AC$6:$AC$105,'Shorts ideas'!$M$6:$M$105,$A21,'Shorts ideas'!$AC$6:$AC$105,">0"),"") | D21: =IFERROR(AVERAGEIFS('Shorts ideas'!$U$6:$U$105,'Shorts ideas'!$M$6:$M$105,$A21,'Shorts ideas'!$U$6:$U$105,">0"),"") | E21: =IFERROR(AVERAGEIFS('Shorts ideas'!$AD$6:$AD$105,'Shorts ideas'!$M$6:$M$105,$A21,'Shorts ideas'!$AD$6:$AD$105,">0"),"") | F21: =IFERROR(AVERAGEIFS('Shorts ideas'!$AL$6:$AL$105,'Shorts ideas'!$M$6:$M$105,$A21,'Shorts ideas'!$AL$6:$AL$105,">0"),"")
A22: Tue | B22: =COUNTIFS('Shorts ideas'!$M$6:$M$105,$A22,'Shorts ideas'!$H$6:$H$105,"Published") | C22: =IFERROR(AVERAGEIFS('Shorts ideas'!$AC$6:$AC$105,'Shorts ideas'!$M$6:$M$105,$A22,'Shorts ideas'!$AC$6:$AC$105,">0"),"") | D22: =IFERROR(AVERAGEIFS('Shorts ideas'!$U$6:$U$105,'Shorts ideas'!$M$6:$M$105,$A22,'Shorts ideas'!$U$6:$U$105,">0"),"") | E22: =IFERROR(AVERAGEIFS('Shorts ideas'!$AD$6:$AD$105,'Shorts ideas'!$M$6:$M$105,$A22,'Shorts ideas'!$AD$6:$AD$105,">0"),"") | F22: =IFERROR(AVERAGEIFS('Shorts ideas'!$AL$6:$AL$105,'Shorts ideas'!$M$6:$M$105,$A22,'Shorts ideas'!$AL$6:$AL$105,">0"),"")
A23: Wed | B23: =COUNTIFS('Shorts ideas'!$M$6:$M$105,$A23,'Shorts ideas'!$H$6:$H$105,"Published") | C23: =IFERROR(AVERAGEIFS('Shorts ideas'!$AC$6:$AC$105,'Shorts ideas'!$M$6:$M$105,$A23,'Shorts ideas'!$AC$6:$AC$105,">0"),"") | D23: =IFERROR(AVERAGEIFS('Shorts ideas'!$U$6:$U$105,'Shorts ideas'!$M$6:$M$105,$A23,'Shorts ideas'!$U$6:$U$105,">0"),"") | E23: =IFERROR(AVERAGEIFS('Shorts ideas'!$AD$6:$AD$105,'Shorts ideas'!$M$6:$M$105,$A23,'Shorts ideas'!$AD$6:$AD$105,">0"),"") | F23: =IFERROR(AVERAGEIFS('Shorts ideas'!$AL$6:$AL$105,'Shorts ideas'!$M$6:$M$105,$A23,'Shorts ideas'!$AL$6:$AL$105,">0"),"")
A24: Thu | B24: =COUNTIFS('Shorts ideas'!$M$6:$M$105,$A24,'Shorts ideas'!$H$6:$H$105,"Published") | C24: =IFERROR(AVERAGEIFS('Shorts ideas'!$AC$6:$AC$105,'Shorts ideas'!$M$6:$M$105,$A24,'Shorts ideas'!$AC$6:$AC$105,">0"),"") | D24: =IFERROR(AVERAGEIFS('Shorts ideas'!$U$6:$U$105,'Shorts ideas'!$M$6:$M$105,$A24,'Shorts ideas'!$U$6:$U$105,">0"),"") | E24: =IFERROR(AVERAGEIFS('Shorts ideas'!$AD$6:$AD$105,'Shorts ideas'!$M$6:$M$105,$A24,'Shorts ideas'!$AD$6:$AD$105,">0"),"") | F24: =IFERROR(AVERAGEIFS('Shorts ideas'!$AL$6:$AL$105,'Shorts ideas'!$M$6:$M$105,$A24,'Shorts ideas'!$AL$6:$AL$105,">0"),"")
A25: Fri | B25: =COUNTIFS('Shorts ideas'!$M$6:$M$105,$A25,'Shorts ideas'!$H$6:$H$105,"Published") | C25: =IFERROR(AVERAGEIFS('Shorts ideas'!$AC$6:$AC$105,'Shorts ideas'!$M$6:$M$105,$A25,'Shorts ideas'!$AC$6:$AC$105,">0"),"") | D25: =IFERROR(AVERAGEIFS('Shorts ideas'!$U$6:$U$105,'Shorts ideas'!$M$6:$M$105,$A25,'Shorts ideas'!$U$6:$U$105,">0"),"") | E25: =IFERROR(AVERAGEIFS('Shorts ideas'!$AD$6:$AD$105,'Shorts ideas'!$M$6:$M$105,$A25,'Shorts ideas'!$AD$6:$AD$105,">0"),"") | F25: =IFERROR(AVERAGEIFS('Shorts ideas'!$AL$6:$AL$105,'Shorts ideas'!$M$6:$M$105,$A25,'Shorts ideas'!$AL$6:$AL$105,">0"),"")
A26: Sat | B26: =COUNTIFS('Shorts ideas'!$M$6:$M$105,$A26,'Shorts ideas'!$H$6:$H$105,"Published") | C26: =IFERROR(AVERAGEIFS('Shorts ideas'!$AC$6:$AC$105,'Shorts ideas'!$M$6:$M$105,$A26,'Shorts ideas'!$AC$6:$AC$105,">0"),"") | D26: =IFERROR(AVERAGEIFS('Shorts ideas'!$U$6:$U$105,'Shorts ideas'!$M$6:$M$105,$A26,'Shorts ideas'!$U$6:$U$105,">0"),"") | E26: =IFERROR(AVERAGEIFS('Shorts ideas'!$AD$6:$AD$105,'Shorts ideas'!$M$6:$M$105,$A26,'Shorts ideas'!$AD$6:$AD$105,">0"),"") | F26: =IFERROR(AVERAGEIFS('Shorts ideas'!$AL$6:$AL$105,'Shorts ideas'!$M$6:$M$105,$A26,'Shorts ideas'!$AL$6:$AL$105,">0"),"")
A27: Sun | B27: =COUNTIFS('Shorts ideas'!$M$6:$M$105,$A27,'Shorts ideas'!$H$6:$H$105,"Published") | C27: =IFERROR(AVERAGEIFS('Shorts ideas'!$AC$6:$AC$105,'Shorts ideas'!$M$6:$M$105,$A27,'Shorts ideas'!$AC$6:$AC$105,">0"),"") | D27: =IFERROR(AVERAGEIFS('Shorts ideas'!$U$6:$U$105,'Shorts ideas'!$M$6:$M$105,$A27,'Shorts ideas'!$U$6:$U$105,">0"),"") | E27: =IFERROR(AVERAGEIFS('Shorts ideas'!$AD$6:$AD$105,'Shorts ideas'!$M$6:$M$105,$A27,'Shorts ideas'!$AD$6:$AD$105,">0"),"") | F27: =IFERROR(AVERAGEIFS('Shorts ideas'!$AL$6:$AL$105,'Shorts ideas'!$M$6:$M$105,$A27,'Shorts ideas'!$AL$6:$AL$105,">0"),"")
A29: Template fit | B29: Published | C29: Avg views d7 | D29: Avg retention d7 | E29: Avg engagement d7 | F29: Avg views d30
A30: Strong | B30: =COUNTIFS('Shorts ideas'!$J$6:$J$105,$A30,'Shorts ideas'!$H$6:$H$105,"Published") | C30: =IFERROR(AVERAGEIFS('Shorts ideas'!$AC$6:$AC$105,'Shorts ideas'!$J$6:$J$105,$A30,'Shorts ideas'!$AC$6:$AC$105,">0"),"") | D30: =IFERROR(AVERAGEIFS('Shorts ideas'!$U$6:$U$105,'Shorts ideas'!$J$6:$J$105,$A30,'Shorts ideas'!$U$6:$U$105,">0"),"") | E30: =IFERROR(AVERAGEIFS('Shorts ideas'!$AD$6:$AD$105,'Shorts ideas'!$J$6:$J$105,$A30,'Shorts ideas'!$AD$6:$AD$105,">0"),"") | F30: =IFERROR(AVERAGEIFS('Shorts ideas'!$AL$6:$AL$105,'Shorts ideas'!$J$6:$J$105,$A30,'Shorts ideas'!$AL$6:$AL$105,">0"),"")
A31: Weak | B31: =COUNTIFS('Shorts ideas'!$J$6:$J$105,$A31,'Shorts ideas'!$H$6:$H$105,"Published") | C31: =IFERROR(AVERAGEIFS('Shorts ideas'!$AC$6:$AC$105,'Shorts ideas'!$J$6:$J$105,$A31,'Shorts ideas'!$AC$6:$AC$105,">0"),"") | D31: =IFERROR(AVERAGEIFS('Shorts ideas'!$U$6:$U$105,'Shorts ideas'!$J$6:$J$105,$A31,'Shorts ideas'!$U$6:$U$105,">0"),"") | E31: =IFERROR(AVERAGEIFS('Shorts ideas'!$AD$6:$AD$105,'Shorts ideas'!$J$6:$J$105,$A31,'Shorts ideas'!$AD$6:$AD$105,">0"),"") | F31: =IFERROR(AVERAGEIFS('Shorts ideas'!$AL$6:$AL$105,'Shorts ideas'!$J$6:$J$105,$A31,'Shorts ideas'!$AL$6:$AL$105,">0"),"")
